reinforcement_pretraining-0.2.0.dist-info/licenses/LICENSE
rpt/__init__.py
rpt/core/__init__.py
rpt/core/advanced_models.py
rpt/core/reward_system.py
rpt/core/rpt_model.py
rpt/core/rpt_trainer.py
rpt/examples/advanced_scaling.py
rpt/examples/basic_pretraining.py
rpt/utils/__init__.py
rpt/utils/curriculum.py
rpt/utils/data_utils.py
rpt/utils/distributed.py
rpt/utils/metrics.py
rpt/utils/scaling.py
reinforcement_pretraining-0.2.0.dist-info/METADATA
reinforcement_pretraining-0.2.0.dist-info/WHEEL
reinforcement_pretraining-0.2.0.dist-info/entry_points.txt
reinforcement_pretraining-0.2.0.dist-info/top_level.txt
reinforcement_pretraining-0.2.0.dist-info/RECORD
