Metadata-Version: 2.4
Name: reinforcement-pretraining
Version: 0.2.0
Summary: Reinforcement Pre-Training for Language Models - Implementation of ArXiv:2506.08007
Home-page: https://github.com/your-username/reinforcement-pretraining
Author: RPT Package Authors
Author-email: 
Maintainer: RPT Package Authors
License: MIT
Project-URL: Homepage, https://github.com/ProCreations-Official/reinforcement-pretraining
Project-URL: Documentation, https://github.com/ProCreations-Official/reinforcement-pretraining#readme
Project-URL: Repository, https://github.com/ProCreations-Official/reinforcement-pretraining
Project-URL: Issues, https://github.com/ProCreations-Official/reinforcement-pretraining/issues
Project-URL: Paper, https://arxiv.org/abs/2506.08007
Keywords: reinforcement learning,language models,pre-training,AI,NLP,deep learning
Classifier: Development Status :: 3 - Alpha
Classifier: Intended Audience :: Developers
Classifier: Intended Audience :: Science/Research
Classifier: Topic :: Scientific/Engineering :: Artificial Intelligence
Classifier: Topic :: Software Development :: Libraries :: Python Modules
Classifier: License :: OSI Approved :: MIT License
Classifier: Programming Language :: Python :: 3
Classifier: Programming Language :: Python :: 3.8
Classifier: Programming Language :: Python :: 3.9
Classifier: Programming Language :: Python :: 3.10
Classifier: Programming Language :: Python :: 3.11
Classifier: Operating System :: OS Independent
Requires-Python: >=3.8
License-File: LICENSE
Requires-Dist: torch>=2.0.0
Requires-Dist: transformers>=4.30.0
Requires-Dist: numpy>=1.21.0
Requires-Dist: tqdm>=4.64.0
Requires-Dist: psutil>=5.9.0
Requires-Dist: datasets>=2.12.0
Requires-Dist: tokenizers>=0.13.0
Requires-Dist: GPUtil>=1.4.0
Requires-Dist: pyyaml>=6.0
Requires-Dist: tensorboard>=2.13.0
Requires-Dist: scipy>=1.9.0
Requires-Dist: scikit-learn>=1.3.0
Requires-Dist: accelerate>=0.20.0
Requires-Dist: matplotlib>=3.5.0
Requires-Dist: seaborn>=0.11.0
Provides-Extra: dev
Requires-Dist: pytest>=6.0; extra == "dev"
Requires-Dist: pytest-cov; extra == "dev"
Requires-Dist: black; extra == "dev"
Requires-Dist: flake8; extra == "dev"
Requires-Dist: isort; extra == "dev"
Requires-Dist: mypy; extra == "dev"
Provides-Extra: viz
Requires-Dist: matplotlib>=3.5.0; extra == "viz"
Requires-Dist: seaborn>=0.11.0; extra == "viz"
Requires-Dist: plotly>=5.0.0; extra == "viz"
Provides-Extra: distributed
Requires-Dist: deepspeed>=0.9.0; extra == "distributed"
Requires-Dist: accelerate>=0.20.0; extra == "distributed"
Provides-Extra: all
Requires-Dist: pytest>=6.0; extra == "all"
Requires-Dist: pytest-cov; extra == "all"
Requires-Dist: black; extra == "all"
Requires-Dist: flake8; extra == "all"
Requires-Dist: isort; extra == "all"
Requires-Dist: mypy; extra == "all"
Requires-Dist: matplotlib>=3.5.0; extra == "all"
Requires-Dist: seaborn>=0.11.0; extra == "all"
Requires-Dist: plotly>=5.0.0; extra == "all"
Requires-Dist: deepspeed>=0.9.0; extra == "all"
Requires-Dist: accelerate>=0.20.0; extra == "all"
Dynamic: home-page
Dynamic: license-file
Dynamic: requires-python
